openirt/__init__.py
openirt/bayes3PL.py
openirt/clean.py
openirt/cli.py
openirt/graded_model.py
openirt/irt_instance.py
openirt/item_models/__init__.py
openirt/item_models/model.py
openirt/item_models/norm.py
openirt/item_models/pl1.py
openirt/item_models/pl2.py
openirt/item_models/pl2_si.py
openirt/item_models/pl3.py
openirt/jmle/__init__.py
openirt/jmle/norm.py
openirt/jmle/pl1.py
openirt/jmle/pl2.py
openirt/jmle/pl2_si.py
openirt/jmle/pl3.py
openirt/mmle/__init__.py
openirt/mmle/dichotomous.py
openirt/mmle/graded.py
openirt-0.1.11.dist-info/LICENSE
openirt-0.1.11.dist-info/METADATA
openirt-0.1.11.dist-info/WHEEL
openirt-0.1.11.dist-info/top_level.txt
openirt-0.1.11.dist-info/RECORD
