Metadata-Version: 2.1
Name: openirt
Version: 0.1.11
Summary: Item response theory toolkit
Home-page: https://gitlab.com/pleased/item-response-theory-toolkit
Author: Johan Hay
License: GPL-3.0
License-File: LICENSE
